{
 "children": [
  {
   "children": [{
    "children": [],
    "type": "audit"
   }],
   "type": "name"
  },
  {
   "children": [{
    "children": [{
     "children": [{
      "children": [{
       "children": [],
       "type": "0 2 * * *"
      }],
      "type": "cron"
     }],
     "type": "OBJ-NODE"
    }],
    "type": "schedule"
   }],
   "type": "on"
  },
  {
   "children": [{
    "children": [
     {
      "children": [{
       "children": [],
       "type": "ubuntu-latest"
      }],
      "type": "runs-on"
     },
     {
      "children": [
       {
        "children": [
         {
          "children": [{
           "children": [],
           "type": "checkout repository"
          }],
          "type": "name"
         },
         {
          "children": [{
           "children": [],
           "type": "actions/checkout@version"
          }],
          "type": "uses"
         }
        ],
        "type": "OBJ-NODE"
       },
       {
        "children": [
         {
          "children": [{
           "children": [],
           "type": "setup python"
          }],
          "type": "name"
         },
         {
          "children": [{
           "children": [],
           "type": "actions/setup-python@version"
          }],
          "type": "uses"
         },
         {
          "children": [{
           "children": [{
            "children": [],
            "type": "3.9"
           }],
           "type": "python-version"
          }],
          "type": "with"
         }
        ],
        "type": "OBJ-NODE"
       },
       {
        "children": [
         {
          "children": [{
           "children": [],
           "type": "install pip-audit"
          }],
          "type": "name"
         },
         {
          "children": [{
           "children": [],
           "type": "pip install --upgrade pip pip-audit"
          }],
          "type": "run"
         }
        ],
        "type": "OBJ-NODE"
       },
       {
        "children": [
         {
          "children": [{
           "children": [],
           "type": "install dependencies"
          }],
          "type": "name"
         },
         {
          "children": [{
           "children": [],
           "type": "pip install ."
          }],
          "type": "run"
         }
        ],
        "type": "OBJ-NODE"
       },
       {
        "children": [
         {
          "children": [{
           "children": [],
           "type": "create requirements.txt"
          }],
          "type": "name"
         },
         {
          "children": [{
           "children": [],
           "type": "pip freeze > requirements.txt"
          }],
          "type": "run"
         }
        ],
        "type": "OBJ-NODE"
       },
       {
        "children": [
         {
          "children": [{
           "children": [],
           "type": "audit dependencies"
          }],
          "type": "name"
         },
         {
          "children": [{
           "children": [],
           "type": "pip-audit"
          }],
          "type": "run"
         }
        ],
        "type": "OBJ-NODE"
       }
      ],
      "type": "steps"
     }
    ],
    "type": "audit"
   }],
   "type": "build"
  }
 ],
 "type": "github-file"
}