{
 "children": [
  {
   "children": [{
    "children": [],
    "type": "lint"
   }],
   "type": "name"
  },
  {
   "children": [
    {
     "children": [],
     "type": "push"
    },
    {
     "children": [],
     "type": "pull_request"
    }
   ],
   "type": "on"
  },
  {
   "children": [{
    "children": [
     {
      "children": [{
       "children": [],
       "type": "github.event_name == 'push' || github.event.pull_request.head.repo.full_name != github.repository"
      }],
      "type": "if"
     },
     {
      "children": [{
       "children": [],
       "type": "ubuntu-latest"
      }],
      "type": "runs-on"
     },
     {
      "children": [
       {
        "children": [{
         "children": [{
          "children": [],
          "type": "actions/checkout@version"
         }],
         "type": "uses"
        }],
        "type": "OBJ-NODE"
       },
       {
        "children": [{
         "children": [{
          "children": [],
          "type": "actions/setup-python@version"
         }],
         "type": "uses"
        }],
        "type": "OBJ-NODE"
       },
       {
        "children": [{
         "children": [{
          "children": [],
          "type": "pre-commit/action@version"
         }],
         "type": "uses"
        }],
        "type": "OBJ-NODE"
       }
      ],
      "type": "steps"
     }
    ],
    "type": "build"
   }],
   "type": "build"
  }
 ],
 "type": "github-file"
}