{
 "children": [
  {
   "children": [{
    "children": [],
    "type": "ptypy tests"
   }],
   "type": "name"
  },
  {
   "children": [
    {
     "children": [{
      "children": [{
       "children": [],
       "type": "branch-name"
      }],
      "type": "branches"
     }],
     "type": "push"
    },
    {
     "children": [{
      "children": [
       {
        "children": [],
        "type": "branch-name"
       },
       {
        "children": [],
        "type": "branch-name"
       }
      ],
      "type": "branches"
     }],
     "type": "pull_request"
    },
    {
     "children": [],
     "type": "page_build"
    },
    {
     "children": [{
      "children": [{
       "children": [],
       "type": "created"
      }],
      "type": "types"
     }],
     "type": "release"
    }
   ],
   "type": "on"
  },
  {
   "children": [{
    "children": [
     {
      "children": [{
       "children": [],
       "type": "ubuntu-latest"
      }],
      "type": "runs-on"
     },
     {
      "children": [
       {
        "children": [{
         "children": [],
         "type": "5"
        }],
        "type": "max-parallel"
       },
       {
        "children": [{
         "children": [
          {
           "children": [],
           "type": "3.7"
          },
          {
           "children": [],
           "type": "3.8"
          },
          {
           "children": [],
           "type": "3.9"
          },
          {
           "children": [],
           "type": "3.10"
          }
         ],
         "type": "python-version"
        }],
        "type": "matrix"
       }
      ],
      "type": "strategy"
     },
     {
      "children": [
       {
        "children": [{
         "children": [{
          "children": [],
          "type": "actions/checkout@version"
         }],
         "type": "uses"
        }],
        "type": "OBJ-NODE"
       },
       {
        "children": [
         {
          "children": [{
           "children": [],
           "type": "set up python-cmd"
          }],
          "type": "name"
         },
         {
          "children": [{
           "children": [],
           "type": "actions/setup-python@version"
          }],
          "type": "uses"
         },
         {
          "children": [{
           "children": [{
            "children": [],
            "type": "${{ matrix.python-version }}"
           }],
           "type": "python-version"
          }],
          "type": "with"
         }
        ],
        "type": "OBJ-NODE"
       },
       {
        "children": [
         {
          "children": [{
           "children": [],
           "type": "add conda to system path"
          }],
          "type": "name"
         },
         {
          "children": [{
           "children": [],
           "type": "# $conda is an environment variable pointing to the root of the miniconda directory\\necho-cmd"
          }],
          "type": "run"
         }
        ],
        "type": "OBJ-NODE"
       },
       {
        "children": [
         {
          "children": [{
           "children": [],
           "type": "install dependencies"
          }],
          "type": "name"
         },
         {
          "children": [{
           "children": [],
           "type": "conda env update --file dependencies_core.yml --name base\\n"
          }],
          "type": "run"
         }
        ],
        "type": "OBJ-NODE"
       },
       {
        "children": [
         {
          "children": [{
           "children": [],
           "type": "prepare ptypy"
          }],
          "type": "name"
         },
         {
          "children": [{
           "children": [],
           "type": "# dry install to create ptypy/PATH-OR-URL\\npython-cmd"
          }],
          "type": "run"
         }
        ],
        "type": "OBJ-NODE"
       },
       {
        "children": [
         {
          "children": [{
           "children": [],
           "type": "lint with flake8"
          }],
          "type": "name"
         },
         {
          "children": [{
           "children": [],
           "type": "conda install flake8\\n# stop the build shell-cmd"
          }],
          "type": "run"
         }
        ],
        "type": "OBJ-NODE"
       },
       {
        "children": [
         {
          "children": [{
           "children": [],
           "type": "test with pytest"
          }],
          "type": "name"
         },
         {
          "children": [{
           "children": [],
           "type": "conda install pytest\\nconda install pytest-cov\\n# pytest ptypy/test -v --doctest-modules --junitxml=junit/test-results.xml --cov=ptypy --cov-report=xml --cov-report=html --cov-config=.coveragerc\\npytest -v\\n"
          }],
          "type": "run"
         }
        ],
        "type": "OBJ-NODE"
       }
      ],
      "type": "steps"
     }
    ],
    "type": "build-linux"
   }],
   "type": "build"
  }
 ],
 "type": "github-file"
}