{
 "children": [
  {
   "children": [{
    "children": [],
    "type": "test"
   }],
   "type": "name"
  },
  {
   "children": [
    {
     "children": [],
     "type": "push"
    },
    {
     "children": [],
     "type": "pull_request"
    }
   ],
   "type": "on"
  },
  {
   "children": [
    {
     "children": [
      {
       "children": [{
        "children": [],
        "type": "node.js 17 full"
       }],
       "type": "name"
      },
      {
       "children": [{
        "children": [],
        "type": "ubuntu-latest"
       }],
       "type": "runs-on"
      },
      {
       "children": [
        {
         "children": [
          {
           "children": [{
            "children": [],
            "type": "checkout the repository"
           }],
           "type": "name"
          },
          {
           "children": [{
            "children": [],
            "type": "actions/checkout@version"
           }],
           "type": "uses"
          }
         ],
         "type": "OBJ-NODE"
        },
        {
         "children": [
          {
           "children": [{
            "children": [],
            "type": "install pnpm"
           }],
           "type": "name"
          },
          {
           "children": [{
            "children": [],
            "type": "pnpm/action-setup@version"
           }],
           "type": "uses"
          },
          {
           "children": [{
            "children": [{
             "children": [],
             "type": "latest"
            }],
            "type": "version"
           }],
           "type": "with"
          }
         ],
         "type": "OBJ-NODE"
        },
        {
         "children": [
          {
           "children": [{
            "children": [],
            "type": "install node.js"
           }],
           "type": "name"
          },
          {
           "children": [{
            "children": [],
            "type": "actions/setup-node@version"
           }],
           "type": "uses"
          },
          {
           "children": [
            {
             "children": [{
              "children": [],
              "type": "17"
             }],
             "type": "node-version"
            },
            {
             "children": [{
              "children": [],
              "type": "pnpm"
             }],
             "type": "cache"
            }
           ],
           "type": "with"
          }
         ],
         "type": "OBJ-NODE"
        },
        {
         "children": [
          {
           "children": [{
            "children": [],
            "type": "install dependencies"
           }],
           "type": "name"
          },
          {
           "children": [{
            "children": [],
            "type": "pnpm-cmd"
           }],
           "type": "run"
          }
         ],
         "type": "OBJ-NODE"
        },
        {
         "children": [
          {
           "children": [{
            "children": [],
            "type": "run tests"
           }],
           "type": "name"
          },
          {
           "children": [{
            "children": [],
            "type": "pnpm-cmd"
           }],
           "type": "run"
          },
          {
           "children": [{
            "children": [{
             "children": [],
             "type": "2"
            }],
            "type": "force_color"
           }],
           "type": "env"
          }
         ],
         "type": "OBJ-NODE"
        }
       ],
       "type": "steps"
      }
     ],
     "type": "full"
    },
    {
     "children": [
      {
       "children": [{
        "children": [],
        "type": "ubuntu-latest"
       }],
       "type": "runs-on"
      },
      {
       "children": [{
        "children": [{
         "children": [
          {
           "children": [],
           "type": "16"
          },
          {
           "children": [],
           "type": "14"
          },
          {
           "children": [],
           "type": "12"
          }
         ],
         "type": "node-version"
        }],
        "type": "matrix"
       }],
       "type": "strategy"
      },
      {
       "children": [{
        "children": [],
        "type": "node.js ${{ matrix.node-version }} quick"
       }],
       "type": "name"
      },
      {
       "children": [
        {
         "children": [
          {
           "children": [{
            "children": [],
            "type": "checkout the repository"
           }],
           "type": "name"
          },
          {
           "children": [{
            "children": [],
            "type": "actions/checkout@version"
           }],
           "type": "uses"
          }
         ],
         "type": "OBJ-NODE"
        },
        {
         "children": [
          {
           "children": [{
            "children": [],
            "type": "install pnpm"
           }],
           "type": "name"
          },
          {
           "children": [{
            "children": [],
            "type": "pnpm/action-setup@version"
           }],
           "type": "uses"
          },
          {
           "children": [{
            "children": [{
             "children": [],
             "type": "latest"
            }],
            "type": "version"
           }],
           "type": "with"
          }
         ],
         "type": "OBJ-NODE"
        },
        {
         "children": [
          {
           "children": [{
            "children": [],
            "type": "install node.js ${{ matrix.node-version }}"
           }],
           "type": "name"
          },
          {
           "children": [{
            "children": [],
            "type": "actions/setup-node@version"
           }],
           "type": "uses"
          },
          {
           "children": [
            {
             "children": [{
              "children": [],
              "type": "${{ matrix.node-version }}"
             }],
             "type": "node-version"
            },
            {
             "children": [{
              "children": [],
              "type": "pnpm"
             }],
             "type": "cache"
            }
           ],
           "type": "with"
          }
         ],
         "type": "OBJ-NODE"
        },
        {
         "children": [
          {
           "children": [{
            "children": [],
            "type": "install dependencies"
           }],
           "type": "name"
          },
          {
           "children": [{
            "children": [],
            "type": "pnpm-cmd"
           }],
           "type": "run"
          }
         ],
         "type": "OBJ-NODE"
        },
        {
         "children": [
          {
           "children": [{
            "children": [],
            "type": "run unit tests"
           }],
           "type": "name"
          },
          {
           "children": [{
            "children": [],
            "type": "pnpm-cmd"
           }],
           "type": "run"
          },
          {
           "children": [{
            "children": [{
             "children": [],
             "type": "2"
            }],
            "type": "force_color"
           }],
           "type": "env"
          }
         ],
         "type": "OBJ-NODE"
        }
       ],
       "type": "steps"
      }
     ],
     "type": "short"
    },
    {
     "children": [
      {
       "children": [{
        "children": [],
        "type": "ubuntu-latest"
       }],
       "type": "runs-on"
      },
      {
       "children": [{
        "children": [],
        "type": "node.js 10 quick"
       }],
       "type": "name"
      },
      {
       "children": [
        {
         "children": [
          {
           "children": [{
            "children": [],
            "type": "checkout the repository"
           }],
           "type": "name"
          },
          {
           "children": [{
            "children": [],
            "type": "actions/checkout@version"
           }],
           "type": "uses"
          }
         ],
         "type": "OBJ-NODE"
        },
        {
         "children": [
          {
           "children": [{
            "children": [],
            "type": "install pnpm"
           }],
           "type": "name"
          },
          {
           "children": [{
            "children": [],
            "type": "pnpm/action-setup@version"
           }],
           "type": "uses"
          },
          {
           "children": [{
            "children": [{
             "children": [],
             "type": "3"
            }],
            "type": "version"
           }],
           "type": "with"
          },
          {
           "children": [{
            "children": [{
             "children": [],
             "type": "TRUE"
            }],
            "type": "actions_allow_unsecure_commands"
           }],
           "type": "env"
          }
         ],
         "type": "OBJ-NODE"
        },
        {
         "children": [
          {
           "children": [{
            "children": [],
            "type": "install node.js 10"
           }],
           "type": "name"
          },
          {
           "children": [{
            "children": [],
            "type": "actions/setup-node@version"
           }],
           "type": "uses"
          },
          {
           "children": [{
            "children": [{
             "children": [],
             "type": "10"
            }],
            "type": "node-version"
           }],
           "type": "with"
          }
         ],
         "type": "OBJ-NODE"
        },
        {
         "children": [
          {
           "children": [{
            "children": [],
            "type": "install dependencies"
           }],
           "type": "name"
          },
          {
           "children": [{
            "children": [],
            "type": "pnpm-cmd"
           }],
           "type": "run"
          }
         ],
         "type": "OBJ-NODE"
        },
        {
         "children": [
          {
           "children": [{
            "children": [],
            "type": "run unit tests"
           }],
           "type": "name"
          },
          {
           "children": [{
            "children": [],
            "type": "pnpm-cmd"
           }],
           "type": "run"
          },
          {
           "children": [{
            "children": [{
             "children": [],
             "type": "2"
            }],
            "type": "force_color"
           }],
           "type": "env"
          }
         ],
         "type": "OBJ-NODE"
        }
       ],
       "type": "steps"
      }
     ],
     "type": "old"
    }
   ],
   "type": "build"
  }
 ],
 "type": "github-file"
}