{
 "children": [
  {
   "children": [{
    "children": [],
    "type": "ci"
   }],
   "type": "name"
  },
  {
   "children": [
    {
     "children": [],
     "type": "push"
    },
    {
     "children": [],
     "type": "pull_request"
    }
   ],
   "type": "on"
  },
  {
   "children": [
    {
     "children": [
      {
       "children": [{
        "children": [],
        "type": "ubuntu-latest"
       }],
       "type": "runs-on"
      },
      {
       "children": [
        {
         "children": [{
          "children": [],
          "type": "TRUE"
         }],
         "type": "fail-fast"
        },
        {
         "children": [{
          "children": [
           {
            "children": [
             {
              "children": [{
               "children": [],
               "type": "3.6"
              }],
              "type": "python-version"
             },
             {
              "children": [{
               "children": [],
               "type": "1.1.6"
              }],
              "type": "nautobot-version"
             }
            ],
            "type": "OBJ-NODE"
           },
           {
            "children": [
             {
              "children": [{
               "children": [],
               "type": "3.7"
              }],
              "type": "python-version"
             },
             {
              "children": [{
               "children": [],
               "type": "1.2"
              }],
              "type": "nautobot-version"
             }
            ],
            "type": "OBJ-NODE"
           },
           {
            "children": [
             {
              "children": [{
               "children": [],
               "type": "3.8"
              }],
              "type": "python-version"
             },
             {
              "children": [{
               "children": [],
               "type": "1.3"
              }],
              "type": "nautobot-version"
             }
            ],
            "type": "OBJ-NODE"
           },
           {
            "children": [
             {
              "children": [{
               "children": [],
               "type": "3.9"
              }],
              "type": "python-version"
             },
             {
              "children": [{
               "children": [],
               "type": "1.3"
              }],
              "type": "nautobot-version"
             }
            ],
            "type": "OBJ-NODE"
           }
          ],
          "type": "include"
         }],
         "type": "matrix"
        }
       ],
       "type": "strategy"
      },
      {
       "children": [
        {
         "children": [{
          "children": [],
          "type": "${{ matrix.python-version }}"
         }],
         "type": "python_ver"
        },
        {
         "children": [{
          "children": [],
          "type": "${{ matrix.nautobot-version }}"
         }],
         "type": "nautobot_ver"
        },
        {
         "children": [{
          "children": [],
          "type": "TRUE"
         }],
         "type": "invoke_local"
        }
       ],
       "type": "env"
      },
      {
       "children": [
        {
         "children": [
          {
           "children": [{
            "children": [],
            "type": "check out repository code"
           }],
           "type": "name"
          },
          {
           "children": [{
            "children": [],
            "type": "actions/checkout@version"
           }],
           "type": "uses"
          }
         ],
         "type": "OBJ-NODE"
        },
        {
         "children": [
          {
           "children": [{
            "children": [],
            "type": "install cicd-cmd"
           }],
           "type": "name"
          },
          {
           "children": [{
            "children": [],
            "type": "pip install -u pip && pip install poetry"
           }],
           "type": "run"
          }
         ],
         "type": "OBJ-NODE"
        },
        {
         "children": [
          {
           "children": [{
            "children": [],
            "type": "install project dependencies via poetry"
           }],
           "type": "name"
          },
          {
           "children": [{
            "children": [],
            "type": "poetry install"
           }],
           "type": "run"
          }
         ],
         "type": "OBJ-NODE"
        },
        {
         "children": [
          {
           "children": [{
            "children": [],
            "type": "start containers"
           }],
           "type": "name"
          },
          {
           "children": [{
            "children": [],
            "type": "poetry run invoke start"
           }],
           "type": "run"
          }
         ],
         "type": "OBJ-NODE"
        },
        {
         "children": [
          {
           "children": [{
            "children": [],
            "type": "wait for-cmd"
           }],
           "type": "name"
          },
          {
           "children": [{
            "children": [],
            "type": "timeout 300 bash -c 'while [[ \\\"$(curl-cmd"
           }],
           "type": "run"
          }
         ],
         "type": "OBJ-NODE"
        },
        {
         "children": [
          {
           "children": [{
            "children": [],
            "type": "tests"
           }],
           "type": "name"
          },
          {
           "children": [{
            "children": [],
            "type": "poetry run invoke tests"
           }],
           "type": "run"
          }
         ],
         "type": "OBJ-NODE"
        }
       ],
       "type": "steps"
      }
     ],
     "type": "tests"
    },
    {
     "children": [
      {
       "children": [{
        "children": [],
        "type": "push package to pypi"
       }],
       "type": "name"
      },
      {
       "children": [{
        "children": [],
        "type": "ubuntu-latest"
       }],
       "type": "runs-on"
      },
      {
       "children": [{
        "children": [],
        "type": "startswith(github.ref, 'refs/tags/v')"
       }],
       "type": "if"
      },
      {
       "children": [
        {
         "children": [
          {
           "children": [{
            "children": [],
            "type": "check out repository code"
           }],
           "type": "name"
          },
          {
           "children": [{
            "children": [],
            "type": "actions/checkout@version"
           }],
           "type": "uses"
          }
         ],
         "type": "OBJ-NODE"
        },
        {
         "children": [
          {
           "children": [{
            "children": [],
            "type": "set up python"
           }],
           "type": "name"
          },
          {
           "children": [{
            "children": [],
            "type": "actions/setup-python@version"
           }],
           "type": "uses"
          },
          {
           "children": [{
            "children": [{
             "children": [],
             "type": "3.9"
            }],
            "type": "python-version"
           }],
           "type": "with"
          }
         ],
         "type": "OBJ-NODE"
        },
        {
         "children": [
          {
           "children": [{
            "children": [],
            "type": "install python-cmd"
           }],
           "type": "name"
          },
          {
           "children": [{
            "children": [],
            "type": "pip install poetry"
           }],
           "type": "run"
          }
         ],
         "type": "OBJ-NODE"
        },
        {
         "children": [
          {
           "children": [{
            "children": [],
            "type": "set env"
           }],
           "type": "name"
          },
          {
           "children": [{
            "children": [],
            "type": "echo-cmd"
           }],
           "type": "run"
          }
         ],
         "type": "OBJ-NODE"
        },
        {
         "children": [
          {
           "children": [{
            "children": [],
            "type": "run poetry version"
           }],
           "type": "name"
          },
          {
           "children": [{
            "children": [],
            "type": "poetry version $release_version"
           }],
           "type": "run"
          }
         ],
         "type": "OBJ-NODE"
        },
        {
         "children": [
          {
           "children": [{
            "children": [],
            "type": "run poetry build"
           }],
           "type": "name"
          },
          {
           "children": [{
            "children": [],
            "type": "poetry build"
           }],
           "type": "run"
          }
         ],
         "type": "OBJ-NODE"
        },
        {
         "children": [
          {
           "children": [{
            "children": [],
            "type": "push to pypi"
           }],
           "type": "name"
          },
          {
           "children": [{
            "children": [],
            "type": "pypa/gh-action-pypi-publish@version"
           }],
           "type": "uses"
          },
          {
           "children": [
            {
             "children": [{
              "children": [],
              "type": "__token__"
             }],
             "type": "user"
            },
            {
             "children": [{
              "children": [],
              "type": "${{ secrets.pypi_api_token }}"
             }],
             "type": "password"
            }
           ],
           "type": "with"
          }
         ],
         "type": "OBJ-NODE"
        }
       ],
       "type": "steps"
      },
      {
       "children": [{
        "children": [],
        "type": "tests"
       }],
       "type": "needs"
      }
     ],
     "type": "publish_pypi"
    }
   ],
   "type": "build"
  }
 ],
 "type": "github-file"
}