{
 "children": [
  {
   "children": [{
    "children": [],
    "type": "docs build test"
   }],
   "type": "name"
  },
  {
   "children": [
    {
     "children": [],
     "type": "push"
    },
    {
     "children": [],
     "type": "pull_request"
    }
   ],
   "type": "on"
  },
  {
   "children": [{
    "children": [
     {
      "children": [{
       "children": [],
       "type": "ubuntu-latest"
      }],
      "type": "runs-on"
     },
     {
      "children": [{
       "children": [{
        "children": [{
         "children": [],
         "type": "14"
        }],
        "type": "node-version"
       }],
       "type": "matrix"
      }],
      "type": "strategy"
     },
     {
      "children": [
       {
        "children": [{
         "children": [{
          "children": [],
          "type": "actions/checkout@version"
         }],
         "type": "uses"
        }],
        "type": "OBJ-NODE"
       },
       {
        "children": [{
         "children": [{
          "children": [],
          "type": "use node.js ${{ matrix.node-version }}"
         }],
         "type": "name"
        }],
        "type": "OBJ-NODE"
       },
       {
        "children": [{
         "children": [{
          "children": [],
          "type": "actions/setup-node@version"
         }],
         "type": "uses"
        }],
        "type": "OBJ-NODE"
       },
       {
        "children": [
         {
          "children": [{
           "children": [],
           "type": "npm-cmd"
          }],
          "type": "name"
         },
         {
          "children": [{
           "children": [],
           "type": "npm-cmd"
          }],
          "type": "run"
         }
        ],
        "type": "OBJ-NODE"
       },
       {
        "children": [
         {
          "children": [{
           "children": [],
           "type": "build docs"
          }],
          "type": "name"
         },
         {
          "children": [{
           "children": [],
           "type": "node data/_utils/pkg && grunt"
          }],
          "type": "run"
         }
        ],
        "type": "OBJ-NODE"
       }
      ],
      "type": "steps"
     }
    ],
    "type": "build"
   }],
   "type": "build"
  }
 ],
 "type": "github-file"
}