{
 "children": [
  {
   "children": [{
    "children": [],
    "type": "python"
   }],
   "type": "language"
  },
  {
   "children": [{
    "children": [{
     "children": [
      {
       "children": [],
       "type": "graphviz"
      },
      {
       "children": [],
       "type": "libgfortran3"
      },
      {
       "children": [],
       "type": "libxkbcommon-x11-0"
      }
     ],
     "type": "packages"
    }],
    "type": "apt"
   }],
   "type": "addons"
  },
  {
   "children": [{
    "children": [
     {
      "children": [],
      "type": "setup_xvfb=true"
     },
     {
      "children": [],
      "type": "on_travis=true"
     },
     {
      "children": [],
      "type": "toxenv=''"
     },
     {
      "children": [],
      "type": "toxargs=''"
     },
     {
      "children": [],
      "type": "toxposargs=''"
     }
    ],
    "type": "global"
   }],
   "type": "env"
  },
  {
   "children": [{
    "children": [
     {
      "children": [
       {
        "children": [{
         "children": [],
         "type": "3.7"
        }],
        "type": "python"
       },
       {
        "children": [{
         "children": [],
         "type": "toxenv='py37-test'"
        }],
        "type": "env"
       },
       {
        "children": [{
         "children": [],
         "type": "python-cmd"
        }],
        "type": "name"
       }
      ],
      "type": "OBJ-NODE"
     },
     {
      "children": [
       {
        "children": [{
         "children": [],
         "type": "3.7"
        }],
        "type": "python"
       },
       {
        "children": [{
         "children": [],
         "type": "toxenv='py37-test-novis'"
        }],
        "type": "env"
       },
       {
        "children": [{
         "children": [],
         "type": "python-cmd"
        }],
        "type": "name"
       }
      ],
      "type": "OBJ-NODE"
     },
     {
      "children": [
       {
        "children": [{
         "children": [],
         "type": "3.6"
        }],
        "type": "python"
       },
       {
        "children": [{
         "children": [],
         "type": "toxenv='py36-test-casa'"
        }],
        "type": "env"
       },
       {
        "children": [{
         "children": [],
         "type": "python-cmd"
        }],
        "type": "name"
       }
      ],
      "type": "OBJ-NODE"
     },
     {
      "children": [
       {
        "children": [{
         "children": [],
         "type": "3.8"
        }],
        "type": "python"
       },
       {
        "children": [{
         "children": [],
         "type": "toxenv='py38-test-novis-dev'"
        }],
        "type": "env"
       },
       {
        "children": [{
         "children": [],
         "type": "python-cmd"
        }],
        "type": "name"
       }
      ],
      "type": "OBJ-NODE"
     },
     {
      "children": [
       {
        "children": [{
         "children": [],
         "type": "c"
        }],
        "type": "language"
       },
       {
        "children": [{
         "children": [],
         "type": "osx"
        }],
        "type": "os"
       },
       {
        "children": [{
         "children": [],
         "type": "python_version=3.7 toxenv='py37-test-novis'"
        }],
        "type": "env"
       },
       {
        "children": [{
         "children": [],
         "type": "python-cmd"
        }],
        "type": "name"
       }
      ],
      "type": "OBJ-NODE"
     },
     {
      "children": [
       {
        "children": [{
         "children": [],
         "type": "c"
        }],
        "type": "language"
       },
       {
        "children": [{
         "children": [],
         "type": "windows"
        }],
        "type": "os"
       },
       {
        "children": [{
         "children": [],
         "type": "python_version=3.7 toxenv='py37-test-all-dev'"
        }],
        "type": "env"
       },
       {
        "children": [{
         "children": [],
         "type": "python-cmd"
        }],
        "type": "name"
       }
      ],
      "type": "OBJ-NODE"
     },
     {
      "children": [
       {
        "children": [{
         "children": [],
         "type": "3.8"
        }],
        "type": "python"
       },
       {
        "children": [{
         "children": [],
         "type": "toxenv='build_docs'"
        }],
        "type": "env"
       },
       {
        "children": [{
         "children": [],
         "type": "documentation"
        }],
        "type": "name"
       }
      ],
      "type": "OBJ-NODE"
     }
    ],
    "type": "include"
   }],
   "type": "matrix"
  },
  {
   "children": [
    {
     "children": [],
     "type": "git fetch --unshallow ."
    },
    {
     "children": [],
     "type": "git fetch --depth=1000000"
    },
    {
     "children": [],
     "type": "shell-cmd"
    }
   ],
   "type": "before_install"
  },
  {
   "children": [{
    "children": [],
    "type": "shell-cmd"
   }],
   "type": "install"
  },
  {
   "children": [
    {
     "children": [],
     "type": "pip install tox"
    },
    {
     "children": [],
     "type": "tox $toxargs -- $toxposargs"
    }
   ],
   "type": "script"
  },
  {
   "children": [
    {
     "children": [],
     "type": "pip install coveralls coverage"
    },
    {
     "children": [],
     "type": "coverage-cmd"
    },
    {
     "children": [],
     "type": "coverage-cmd"
    },
    {
     "children": [],
     "type": "coveralls"
    }
   ],
   "type": "after_success"
  }
 ],
 "type": "travis-file"
}